restful_api/__init__.py
restful_api/api_sanic.py
restful_api-0.0.4.dist-info/LICENSE
restful_api-0.0.4.dist-info/METADATA
restful_api-0.0.4.dist-info/WHEEL
restful_api-0.0.4.dist-info/top_level.txt
restful_api-0.0.4.dist-info/RECORD
