Metadata-Version: 2.1
Name: restful-api
Version: 0.0.4
Summary: Simple Model Deploy Restful Api!
Home-page: https://github.com/Jie-Yuan/RestfulApi
Author: YuanJie
Author-email: 313303303@qq.com
Maintainer: YuanJie
Maintainer-email: 313303303@qq.com
License: MIT
Keywords: restful_api
Platform: all
Classifier: Development Status :: 4 - Beta
Classifier: Operating System :: OS Independent
Classifier: Intended Audience :: Developers
Classifier: License :: OSI Approved :: MIT License
Classifier: Programming Language :: Python :: Implementation
Classifier: Programming Language :: Python :: 3.6
Classifier: Topic :: Software Development :: Libraries
Requires-Python: >=3.6
Requires-Dist: vibora
Requires-Dist: sanic
